<DOMSymbolItem xmlns:xsi="http://www.w3.org/2001/XMLSchema-instance" xmlns="http://ns.adobe.com/xfl/2008/" name="switch_today_mask" itemID="4d38d665-00000237" sourceLibraryItemHRef="Symbol 1" lastModified="1295652044">
  <timeline>
    <DOMTimeline name="switch_today_mask">
      <layers>
        <DOMLayer name="Layer 1" color="#4FFF4F" current="true" isSelected="true">
          <frames>
            <DOMFrame index="0" keyMode="9728">
              <elements>
                <DOMShape isDrawingObject="true">
                  <matrix>
                    <Matrix tx="-2"/>
                  </matrix>
                  <transformationPoint>
                    <Point/>
                  </transformationPoint>
                  <fills>
                    <FillStyle index="1">
                      <SolidColor color="#FFFF00"/>
                    </FillStyle>
                  </fills>
                  <edges>
                    <Edge fillStyle0="1" edges="!240 -721|-2960 -721!-2960 -721|-2960 4281!-2960 4281|240 4281!240 4281|240 -721"/>
                  </edges>
                </DOMShape>
              </elements>
            </DOMFrame>
          </frames>
        </DOMLayer>
      </layers>
    </DOMTimeline>
  </timeline>
</DOMSymbolItem>